my_arsenal_addons/__init__.py
my_arsenal_addons/custom_cheats.py
my_arsenal_addons/cheats/fscan.md
my_arsenal_addons/cheats/xray.md
my_arsenal_addons-0.1.0.dist-info/METADATA
my_arsenal_addons-0.1.0.dist-info/WHEEL
my_arsenal_addons-0.1.0.dist-info/entry_points.txt
my_arsenal_addons-0.1.0.dist-info/top_level.txt
my_arsenal_addons-0.1.0.dist-info/RECORD
