Metadata-Version: 2.4
Name: my-arsenal-addons
Version: 0.1.0
Summary: 一键部署自定义 cheatsheets 到 Arsenal 工具的自定义命令目录
Home-page: https://github.com/yourname/my-arsenal-addons
Author: Your Name
Author-email: your@email.com
Classifier: Programming Language :: Python :: 3
Classifier: License :: OSI Approved :: MIT License
Classifier: Operating System :: OS Independent
Dynamic: author
Dynamic: author-email
Dynamic: classifier
Dynamic: home-page
Dynamic: summary
